repo_helper_rtd/__init__.py
repo_helper_rtd/cli.py
repo_helper_rtd/options.py
repo_helper_rtd-0.1.1.dist-info/LICENSE
repo_helper_rtd-0.1.1.dist-info/METADATA
repo_helper_rtd-0.1.1.dist-info/WHEEL
repo_helper_rtd-0.1.1.dist-info/entry_points.txt
repo_helper_rtd-0.1.1.dist-info/RECORD
