Metadata-Version: 2.1
Name: repo-helper-rtd
Version: 0.1.1
Summary: Manage ReadTheDocs documentation with repo-helper.
Author-email: Dominic Davis-Foster <dominic@davis-foster.co.uk>
License: MIT
Keywords: readthedocs,repo-helper,rtd
Home-page: https://github.com/repo-helper/repo_helper_rtd
Project-URL: Issue Tracker, https://github.com/repo-helper/repo_helper_rtd/issues
Project-URL: Source Code, https://github.com/repo-helper/repo_helper_rtd
Project-URL: Documentation, https://repo-helper-rtd.readthedocs.io/en/latest
Platform: Windows
Platform: macOS
Platform: Linux
Classifier: License :: OSI Approved :: MIT License
Classifier: Operating System :: OS Independent
Classifier: Programming Language :: Python
Classifier: Programming Language :: Python :: 3 :: Only
Classifier: Programming Language :: Python :: 3.6
Classifier: Programming Language :: Python :: 3.7
Classifier: Programming Language :: Python :: 3.8
Classifier: Programming Language :: Python :: 3.9
Classifier: Programming Language :: Python :: 3.10
Classifier: Programming Language :: Python :: 3.11
Classifier: Programming Language :: Python :: Implementation :: CPython
Requires-Python: >=3.6
Requires-Dist: apeye>=0.5.0
Requires-Dist: click>=7.1.2
Requires-Dist: consolekit>=0.8.2
Requires-Dist: domdf-python-tools>=1.6.0
Requires-Dist: repo-helper>=2020.12.2
Requires-Dist: requests>=2.25.0
